itis
