Metadata-Version: 1.0
Name: itis
Version: 2.0.0
Summary: Check whether a website is up or down
Home-page: http://github.com/akashnimare/itis/
Author: Akash Nimare
Author-email: svnitakash@gmail.com
License: MIT
Keywords: website status website down website up internet check command line too
Platform: UNKNOWN
